npdi_oas/agencies.py
npdi_oas/complaints.py
npdi_oas/error.py
npdi_oas/litigation.py
npdi_oas/officers.py
npdi_oas/pagination.py
npdi_oas/sources.py
npdi_oas/users.py
npdi_oas-0.0.4.dist-info/METADATA
npdi_oas-0.0.4.dist-info/WHEEL
npdi_oas-0.0.4.dist-info/top_level.txt
npdi_oas-0.0.4.dist-info/RECORD
