Metadata-Version: 2.4
Name: npdi_oas
Version: 0.0.4
Summary: OpenAPI spec for NPDI data models
Home-page: https://github.com/codeforboston/police-data-trust/tree/main/oas
Author: zganger
Author-email: zganger@icloud.com
Requires-Dist: pydantic
Dynamic: author
Dynamic: author-email
Dynamic: description
Dynamic: description-content-type
Dynamic: home-page
Dynamic: requires-dist
Dynamic: summary
